django_omise/__init__.py
django_omise/admin/__init__.py
django_omise/admin/admin.py
django_omise/admin_views.py
django_omise/apps.py
django_omise/context_processors.py
django_omise/forms.py
django_omise/locale/th/LC_MESSAGES/django.po
django_omise/migrations/0001_initial.py
django_omise/migrations/0002_alter_chargeschedule_card.py
django_omise/migrations/0003_alter_source_type.py
django_omise/migrations/0004_auto_20220523_0847.py
django_omise/migrations/0005_alter_charge_options.py
django_omise/migrations/__init__.py
django_omise/mixins.py
django_omise/models/__init__.py
django_omise/models/base.py
django_omise/models/choices.py
django_omise/models/core.py
django_omise/models/event.py
django_omise/models/managers.py
django_omise/models/schedule.py
django_omise/omise.py
django_omise/static/django_omise/css/tailwind_input.css
django_omise/static/django_omise/css/tailwind_output.css
django_omise/static/django_omise/images/creditcardproviders/americanexpress.png
django_omise/static/django_omise/images/creditcardproviders/americanexpress02.png
django_omise/static/django_omise/images/creditcardproviders/cirrus.png
django_omise/static/django_omise/images/creditcardproviders/delta.png
django_omise/static/django_omise/images/creditcardproviders/dinersclub.png
django_omise/static/django_omise/images/creditcardproviders/directdebit.png
django_omise/static/django_omise/images/creditcardproviders/discover.png
django_omise/static/django_omise/images/creditcardproviders/egold.png
django_omise/static/django_omise/images/creditcardproviders/maestro.png
django_omise/static/django_omise/images/creditcardproviders/mastercard.png
django_omise/static/django_omise/images/creditcardproviders/paypal.png
django_omise/static/django_omise/images/creditcardproviders/solo.png
django_omise/static/django_omise/images/creditcardproviders/switch.png
django_omise/static/django_omise/images/creditcardproviders/visa.png
django_omise/static/django_omise/images/creditcardproviders/visa02.png
django_omise-0.2.20.dist-info/LICENSE.txt
django_omise-0.2.20.dist-info/METADATA
django_omise-0.2.20.dist-info/WHEEL
django_omise-0.2.20.dist-info/RECORD
