Metadata-Version: 2.1
Name: django-omise
Version: 0.2.20
Summary: Django models for Omise
Home-page: https://github.com/jamesx00/django-omise
License: MIT
Author: James Tansiri
Author-email: tansirijames@gmail.com
Requires-Python: >=3.8,<4.0
Classifier: License :: OSI Approved :: MIT License
Classifier: Programming Language :: Python :: 3
Classifier: Programming Language :: Python :: 3.8
Classifier: Programming Language :: Python :: 3.9
Classifier: Programming Language :: Python :: 3.10
Classifier: Programming Language :: Python :: 3.11
Classifier: Programming Language :: Python :: 3.12
Requires-Dist: omise (>=0.13.0,<0.14.0)
Requires-Dist: setuptools (>=70.0.0,<71.0.0)
Project-URL: Repository, https://github.com/jamesx00/django-omise
